digital_library_api/__init__.py
digital_library_api/__main__.py
digital_library_api/database.py
digital_library_api/json_api.py
digital_library_api/models.py
digital_library_api/test_dependencies.py
digital_library_api/test_json_api.py
digital_library_gui/__main__.py
digital_library_gui/book_operations.py
digital_library_gui/dialogs.py
digital_library_gui/gui.py
digital_library_gui/ui_setup.py
digital_library_rfid/rfid.py
digital_library_sip2/sip2_demo_client.py
digital_library_sip2/sip2_mock_server.py
digital_library_web/.gitignore
digital_library_web/README.md
digital_library_web/deno.json
digital_library_web/deno.lock
digital_library_web/dev.ts
digital_library_web/main.py
digital_library_web/main.ts
digital_library_web/tailwind.config.ts
digital_library_web/utils.ts
digital_library_web/_fresh/snapshot.json
digital_library_web/_fresh/static/styles.css
digital_library_web/_fresh/static/_fresh/js/d9edc320a42dbe9a6fbc9bbd0089afb0a7adcef1/AddBookForm.js
digital_library_web/_fresh/static/_fresh/js/d9edc320a42dbe9a6fbc9bbd0089afb0a7adcef1/AuthStatus.js
digital_library_web/_fresh/static/_fresh/js/d9edc320a42dbe9a6fbc9bbd0089afb0a7adcef1/BookList.js
digital_library_web/_fresh/static/_fresh/js/d9edc320a42dbe9a6fbc9bbd0089afb0a7adcef1/Counter.js
digital_library_web/_fresh/static/_fresh/js/d9edc320a42dbe9a6fbc9bbd0089afb0a7adcef1/LoginForm.js
digital_library_web/_fresh/static/_fresh/js/d9edc320a42dbe9a6fbc9bbd0089afb0a7adcef1/RegisterForm.js
digital_library_web/_fresh/static/_fresh/js/d9edc320a42dbe9a6fbc9bbd0089afb0a7adcef1/chunk-2E5Q76HC.js
digital_library_web/_fresh/static/_fresh/js/d9edc320a42dbe9a6fbc9bbd0089afb0a7adcef1/chunk-OC3NYLOT.js
digital_library_web/_fresh/static/_fresh/js/d9edc320a42dbe9a6fbc9bbd0089afb0a7adcef1/chunk-TY33ZR3E.js
digital_library_web/_fresh/static/_fresh/js/d9edc320a42dbe9a6fbc9bbd0089afb0a7adcef1/chunk-UNITEU6O.js
digital_library_web/_fresh/static/_fresh/js/d9edc320a42dbe9a6fbc9bbd0089afb0a7adcef1/fresh-runtime.js
digital_library-2025.6.15.3.dist-info/METADATA
digital_library-2025.6.15.3.dist-info/WHEEL
digital_library-2025.6.15.3.dist-info/entry_points.txt
digital_library-2025.6.15.3.dist-info/licenses/LICENSE
digital_library-2025.6.15.3.dist-info/RECORD
