Metadata-Version: 2.4
Name: digital-library
Version: 2025.6.15.3
Summary: demo digital library application
Author-email: Maple <wjxa20152015@gmail.com>
License-File: LICENSE
Requires-Python: >=3.11
Requires-Dist: fastapi>=0.115.12
Requires-Dist: httpx>=0.28.1
Requires-Dist: passlib[bcrypt]>=1.7.4
Requires-Dist: pydantic[email]>=2.11.5
Requires-Dist: pyserial>=3.5
Requires-Dist: pyside6>=6.9.1
Requires-Dist: pytest>=8.4.0
Requires-Dist: python-jose>=3.5.0
Requires-Dist: python-multipart>=0.0.20
Requires-Dist: sodatools>=2025.2.16.0
Requires-Dist: sqlalchemy>=2.0.41
Requires-Dist: uvicorn>=0.34.3
